problee/__init__.py
problee/client.py
problee/exceptions.py
problee/api/__init__.py
problee/api/markets.py
problee/api/positions.py
problee/api/quotes.py
problee/models/__init__.py
problee/models/market.py
problee/models/position.py
problee/models/quote.py
problee/streaming/__init__.py
problee/streaming/sse.py
problee/streaming/websocket.py
problee-0.1.1.dist-info/LICENSE
problee-0.1.1.dist-info/METADATA
problee-0.1.1.dist-info/WHEEL
problee-0.1.1.dist-info/top_level.txt
problee-0.1.1.dist-info/RECORD
