Metadata-Version: 2.1
Name: problee
Version: 0.1.1
Summary: Official Python SDK for the Problee prediction market API
Author-email: Problee <dev@problee.com>
License: MIT
Project-URL: Homepage, https://problee.com
Project-URL: Documentation, https://problee.com/developer/docs
Project-URL: Repository, https://github.com/problee/problee-python
Project-URL: Changelog, https://github.com/problee/problee-python/blob/main/CHANGELOG.md
Keywords: problee,prediction-market,api,sdk,trading,world-chain
Classifier: Development Status :: 4 - Beta
Classifier: Intended Audience :: Developers
Classifier: Operating System :: OS Independent
Classifier: Programming Language :: Python :: 3
Classifier: Programming Language :: Python :: 3.8
Classifier: Programming Language :: Python :: 3.9
Classifier: Programming Language :: Python :: 3.10
Classifier: Programming Language :: Python :: 3.11
Classifier: Programming Language :: Python :: 3.12
Classifier: Topic :: Software Development :: Libraries :: Python Modules
Classifier: Typing :: Typed
Requires-Python: >=3.8
License-File: LICENSE
Requires-Dist: requests>=2.28.0
Provides-Extra: all
Requires-Dist: websockets>=10.0; extra == "all"
Provides-Extra: dev
Requires-Dist: pytest>=7.0; extra == "dev"
Requires-Dist: pytest-asyncio>=0.21.0; extra == "dev"
Requires-Dist: mypy>=1.0; extra == "dev"
Requires-Dist: ruff>=0.1.0; extra == "dev"
Requires-Dist: responses>=0.23.0; extra == "dev"
Provides-Extra: websocket
Requires-Dist: websockets>=10.0; extra == "websocket"
